mysql_tracer/__init__.py
mysql_tracer/__main__.py
mysql_tracer/_configuration.py
mysql_tracer/_query.py
mysql_tracer/_writer.py
mysql_tracer/args_parser.py
mysql_tracer/cursor_provider.py
mysql_tracer-2.0.3.dist-info/LICENSE
mysql_tracer-2.0.3.dist-info/METADATA
mysql_tracer-2.0.3.dist-info/WHEEL
mysql_tracer-2.0.3.dist-info/entry_points.txt
mysql_tracer-2.0.3.dist-info/top_level.txt
mysql_tracer-2.0.3.dist-info/RECORD
