Metadata-Version: 2.1
Name: mysql-tracer
Version: 2.0.3
Summary: A MySQL client to run queries, write execution reports and export results
Home-page: https://github.com/AdrienHorgnies/py-mysql-tracer
Author: Adrien Horgnies
Author-email: adrien.pierre.horgnies@gmail.com
License: MIT License
Download-URL: https://github.com/AdrienHorgnies/py-mysql-tracer/archive/2.0.3.tar.gz
Keywords: mysql,client,report,export
Platform: UNKNOWN
Classifier: Programming Language :: Python :: 3
Classifier: License :: OSI Approved :: MIT License
Classifier: Operating System :: OS Independent
Classifier: Development Status :: 4 - Beta
Classifier: Intended Audience :: Developers
Requires-Dist: mysql-connector-python (==8.0.20)
Requires-Dist: keyring (==19.0.2)
Provides-Extra: dev
Requires-Dist: pytest (==5.0.1) ; extra == 'dev'
Requires-Dist: mock (==3.0.5) ; extra == 'dev'
